[{"id":1,"stock_tickers":"ABT.AX","price_date":"1462723200000","price_close":0.94,"price_high":1.0,"price_low":0.87,"price_open":0.87,"volume":371100.0,"updated_at":"2017-05-09T13:46:21.000Z"},{"id":2,"stock_tickers":"ABT.AX","price_date":"1462809600000","price_close":0.88,"price_high":0.96,"price_low":0.81,"price_open":0.95,"volume":454500.0,"updated_at":"2017-05-09T13:46:21.000Z"},{"id":3,"stock_tickers":"ABT.AX","price_date":"1462896000000","price_close":0.93,"price_high":0.97,"price_low":0.91,"price_open":0.945,"volume":233900.0,"updated_at":"2017-05-09T13:46:21.000Z"},{"id":4,"stock_tickers":"ABT.AX","price_date":"1462982400000","price_close":0.88,"price_high":0.93,"price_low":0.88,"price_open":0.93,"volume":121300.0,"updated_at":"2017-05-09T13:46:21.000Z"},{"id":5,"stock_tickers":"ABT.AX","price_date":"1463068800000","price_close":0.85,"price_high":0.88,"price_low":0.83,"price_open":0.88,"volume":59700.0,"updated_at":"2017-05-09T13:46:21.000Z"},{"id":6,"stock_tickers":"ABT.AX","price_date":"1463328000000","price_close":0.82,"price_high":0.83,"price_low":0.82,"price_open":0.82,"volume":14600.0,"updated_at":"2017-05-09T13:46:21.000Z"},{"id":7,"stock_tickers":"ABT.AX","price_date":"1463414400000","price_close":0.805,"price_high":0.84,"price_low":0.805,"price_open":0.83,"volume":19800.0,"updated_at":"2017-05-09T13:46:21.000Z"},{"id":8,"stock_tickers":"ABT.AX","price_date":"1463500800000","price_close":0.72,"price_high":0.805,"price_low":0.7,"price_open":0.805,"volume":111600.0,"updated_at":"2017-05-09T13:46:21.000Z"},{"id":9,"stock_tickers":"ABT.AX","price_date":"1463587200000","price_close":0.67,"price_high":0.72,"price_low":0.63,"price_open":0.72,"volume":201300.0,"updated_at":"2017-05-09T13:46:21.000Z"},{"id":10,"stock_tickers":"ABT.AX","price_date":"1463673600000","price_close":0.695,"price_high":0.7,"price_low":0.65,"price_open":0.65,"volume":100800.0,"updated_at":"2017-05-09T13:46:21.000Z"},{"id":11,"stock_tickers":"ABT.AX","price_date":"1463932800000","price_close":0.75,"price_high":0.75,"price_low":0.695,"price_open":0.7,"volume":65300.0,"updated_at":"2017-05-09T13:46:21.000Z"},{"id":12,"stock_tickers":"ABT.AX","price_date":"1464019200000","price_close":0.8,"price_high":0.84,"price_low":0.8,"price_open":0.8,"volume":184200.0,"updated_at":"2017-05-09T13:46:21.000Z"},{"id":13,"stock_tickers":"ABT.AX","price_date":"1464105600000","price_close":0.71,"price_high":0.8,"price_low":0.71,"price_open":0.8,"volume":18800.0,"updated_at":"2017-05-09T13:46:21.000Z"},{"id":14,"stock_tickers":"ABT.AX","price_date":"1464192000000","price_close":0.7,"price_high":0.71,"price_low":0.7,"price_open":0.71,"volume":49700.0,"updated_at":"2017-05-09T13:46:21.000Z"},{"id":15,"stock_tickers":"ABT.AX","price_date":"1464278400000","price_close":0.7,"price_high":0.705,"price_low":0.685,"price_open":0.69,"volume":58600.0,"updated_at":"2017-05-09T13:46:21.000Z"},{"id":16,"stock_tickers":"ABT.AX","price_date":"1464537600000","price_close":0.69,"price_high":0.725,"price_low":0.69,"price_open":0.69,"volume":7500.0,"updated_at":"2017-05-09T13:46:21.000Z"},{"id":17,"stock_tickers":"ABT.AX","price_date":"1464624000000","price_close":0.78,"price_high":0.82,"price_low":0.7,"price_open":0.7,"volume":123000.0,"updated_at":"2017-05-09T13:46:21.000Z"},{"id":18,"stock_tickers":"ABT.AX","price_date":"1464710400000","price_close":0.84,"price_high":0.84,"price_low":0.79,"price_open":0.79,"volume":26800.0,"updated_at":"2017-05-09T13:46:21.000Z"},{"id":19,"stock_tickers":"ABT.AX","price_date":"1464796800000","price_close":0.82,"price_high":0.84,"price_low":0.82,"price_open":0.84,"volume":12600.0,"updated_at":"2017-05-09T13:46:21.000Z"},{"id":20,"stock_tickers":"ABT.AX","price_date":"1464883200000","price_close":0.82,"price_high":0.84,"price_low":0.82,"price_open":0.82,"volume":45600.0,"updated_at":"2017-05-09T13:46:21.000Z"},{"id":21,"stock_tickers":"ABT.AX","price_date":"1465142400000","price_close":0.76,"price_high":0.8,"price_low":0.76,"price_open":0.8,"volume":34500.0,"updated_at":"2017-05-09T13:46:21.000Z"},{"id":22,"stock_tickers":"ABT.AX","price_date":"1465228800000","price_close":0.78,"price_high":0.78,"price_low":0.775,"price_open":0.775,"volume":4200.0,"updated_at":"2017-05-09T13:46:21.000Z"},{"id":23,"stock_tickers":"ABT.AX","price_date":"1465315200000","price_close":0.81,"price_high":0.86,"price_low":0.8,"price_open":0.86,"volume":339100.0,"updated_at":"2017-05-09T13:46:21.000Z"},{"id":24,"stock_tickers":"ABT.AX","price_date":"1465401600000","price_close":0.8,"price_high":0.82,"price_low":0.79,"price_open":0.81,"volume":117000.0,"updated_at":"2017-05-09T13:46:21.000Z"},{"id":25,"stock_tickers":"ABT.AX","price_date":"1465488000000","price_close":0.8,"price_high":0.81,"price_low":0.79,"price_open":0.8,"volume":84700.0,"updated_at":"2017-05-09T13:46:21.000Z"},{"id":26,"stock_tickers":"ABT.AX","price_date":"1465747200000","price_close":0.8,"price_high":0.8,"price_low":0.8,"price_open":0.8,"volume":0.0,"updated_at":"2017-05-09T13:46:21.000Z"},{"id":27,"stock_tickers":"ABT.AX","price_date":"1465833600000","price_close":0.78,"price_high":0.805,"price_low":0.76,"price_open":0.805,"volume":80900.0,"updated_at":"2017-05-09T13:46:21.000Z"},{"id":28,"stock_tickers":"ABT.AX","price_date":"1465920000000","price_close":0.83,"price_high":0.83,"price_low":0.795,"price_open":0.8,"volume":106200.0,"updated_at":"2017-05-09T13:46:21.000Z"},{"id":29,"stock_tickers":"ABT.AX","price_date":"1466006400000","price_close":0.83,"price_high":0.86,"price_low":0.83,"price_open":0.83,"volume":29800.0,"updated_at":"2017-05-09T13:46:21.000Z"},{"id":30,"stock_tickers":"ABT.AX","price_date":"1466092800000","price_close":0.83,"price_high":0.86,"price_low":0.83,"price_open":0.85,"volume":61000.0,"updated_at":"2017-05-09T13:46:21.000Z"},{"id":31,"stock_tickers":"ABT.AX","price_date":"1466352000000","price_close":0.8,"price_high":0.83,"price_low":0.8,"price_open":0.83,"volume":16600.0,"updated_at":"2017-05-09T13:46:21.000Z"},{"id":32,"stock_tickers":"ABT.AX","price_date":"1466438400000","price_close":0.815,"price_high":0.815,"price_low":0.81,"price_open":0.81,"volume":18500.0,"updated_at":"2017-05-09T13:46:21.000Z"},{"id":33,"stock_tickers":"ABT.AX","price_date":"1466524800000","price_close":0.8,"price_high":0.82,"price_low":0.8,"price_open":0.815,"volume":46700.0,"updated_at":"2017-05-09T13:46:21.000Z"},{"id":34,"stock_tickers":"ABT.AX","price_date":"1466611200000","price_close":0.8,"price_high":0.84,"price_low":0.8,"price_open":0.815,"volume":22000.0,"updated_at":"2017-05-09T13:46:21.000Z"},{"id":35,"stock_tickers":"ABT.AX","price_date":"1466697600000","price_close":0.8,"price_high":0.81,"price_low":0.8,"price_open":0.8,"volume":75800.0,"updated_at":"2017-05-09T13:46:21.000Z"},{"id":36,"stock_tickers":"ABT.AX","price_date":"1466956800000","price_close":0.8,"price_high":0.8,"price_low":0.78,"price_open":0.8,"volume":77700.0,"updated_at":"2017-05-09T13:46:21.000Z"},{"id":37,"stock_tickers":"ABT.AX","price_date":"1467043200000","price_close":0.81,"price_high":0.81,"price_low":0.79,"price_open":0.8,"volume":86200.0,"updated_at":"2017-05-09T13:46:21.000Z"},{"id":38,"stock_tickers":"ABT.AX","price_date":"1467129600000","price_close":0.9,"price_high":0.9,"price_low":0.81,"price_open":0.81,"volume":190500.0,"updated_at":"2017-05-09T13:46:21.000Z"},{"id":39,"stock_tickers":"ABT.AX","price_date":"1467216000000","price_close":0.94,"price_high":0.95,"price_low":0.9,"price_open":0.9,"volume":39300.0,"updated_at":"2017-05-09T13:46:21.000Z"},{"id":40,"stock_tickers":"ABT.AX","price_date":"1467302400000","price_close":0.96,"price_high":0.965,"price_low":0.925,"price_open":0.94,"volume":89200.0,"updated_at":"2017-05-09T13:46:21.000Z"},{"id":41,"stock_tickers":"ABT.AX","price_date":"1467561600000","price_close":0.95,"price_high":0.97,"price_low":0.95,"price_open":0.965,"volume":74100.0,"updated_at":"2017-05-09T13:46:21.000Z"},{"id":42,"stock_tickers":"ABT.AX","price_date":"1467648000000","price_close":0.9,"price_high":0.95,"price_low":0.9,"price_open":0.95,"volume":96300.0,"updated_at":"2017-05-09T13:46:21.000Z"},{"id":43,"stock_tickers":"ABT.AX","price_date":"1467734400000","price_close":0.955,"price_high":0.96,"price_low":0.94,"price_open":0.94,"volume":54700.0,"updated_at":"2017-05-09T13:46:21.000Z"},{"id":44,"stock_tickers":"ABT.AX","price_date":"1467820800000","price_close":0.905,"price_high":1.0,"price_low":0.905,"price_open":0.96,"volume":125500.0,"updated_at":"2017-05-09T13:46:21.000Z"},{"id":45,"stock_tickers":"ABT.AX","price_date":"1467907200000","price_close":0.87,"price_high":0.92,"price_low":0.87,"price_open":0.905,"volume":43300.0,"updated_at":"2017-05-09T13:46:21.000Z"},{"id":46,"stock_tickers":"ABT.AX","price_date":"1468166400000","price_close":0.88,"price_high":0.94,"price_low":0.88,"price_open":0.9,"volume":35700.0,"updated_at":"2017-05-09T13:46:21.000Z"},{"id":47,"stock_tickers":"ABT.AX","price_date":"1468252800000","price_close":0.9,"price_high":0.9,"price_low":0.88,"price_open":0.9,"volume":20800.0,"updated_at":"2017-05-09T13:46:21.000Z"},{"id":48,"stock_tickers":"ABT.AX","price_date":"1468339200000","price_close":0.825,"price_high":0.9,"price_low":0.825,"price_open":0.9,"volume":132100.0,"updated_at":"2017-05-09T13:46:21.000Z"},{"id":49,"stock_tickers":"ABT.AX","price_date":"1468425600000","price_close":0.84,"price_high":0.85,"price_low":0.835,"price_open":0.835,"volume":58000.0,"updated_at":"2017-05-09T13:46:21.000Z"},{"id":50,"stock_tickers":"ABT.AX","price_date":"1468512000000","price_close":0.855,"price_high":0.9,"price_low":0.85,"price_open":0.85,"volume":22300.0,"updated_at":"2017-05-09T13:46:21.000Z"},{"id":51,"stock_tickers":"ABT.AX","price_date":"1468771200000","price_close":0.855,"price_high":0.875,"price_low":0.855,"price_open":0.86,"volume":19200.0,"updated_at":"2017-05-09T13:46:21.000Z"},{"id":52,"stock_tickers":"ABT.AX","price_date":"1468857600000","price_close":0.85,"price_high":0.85,"price_low":0.83,"price_open":0.85,"volume":17600.0,"updated_at":"2017-05-09T13:46:21.000Z"},{"id":53,"stock_tickers":"ABT.AX","price_date":"1468944000000","price_close":0.825,"price_high":0.85,"price_low":0.825,"price_open":0.85,"volume":14300.0,"updated_at":"2017-05-09T13:46:21.000Z"},{"id":54,"stock_tickers":"ABT.AX","price_date":"1469030400000","price_close":0.81,"price_high":0.85,"price_low":0.81,"price_open":0.85,"volume":5900.0,"updated_at":"2017-05-09T13:46:21.000Z"},{"id":55,"stock_tickers":"ABT.AX","price_date":"1469116800000","price_close":0.8,"price_high":0.81,"price_low":0.8,"price_open":0.8,"volume":46800.0,"updated_at":"2017-05-09T13:46:21.000Z"},{"id":56,"stock_tickers":"ABT.AX","price_date":"1469376000000","price_close":0.8,"price_high":0.8,"price_low":0.8,"price_open":0.8,"volume":5300.0,"updated_at":"2017-05-09T13:46:21.000Z"},{"id":57,"stock_tickers":"ABT.AX","price_date":"1469462400000","price_close":0.835,"price_high":0.835,"price_low":0.81,"price_open":0.81,"volume":25500.0,"updated_at":"2017-05-09T13:46:21.000Z"},{"id":58,"stock_tickers":"ABT.AX","price_date":"1469548800000","price_close":0.86,"price_high":0.875,"price_low":0.86,"price_open":0.865,"volume":47500.0,"updated_at":"2017-05-09T13:46:21.000Z"},{"id":59,"stock_tickers":"ABT.AX","price_date":"1469635200000","price_close":0.84,"price_high":0.84,"price_low":0.8,"price_open":0.84,"volume":38000.0,"updated_at":"2017-05-09T13:46:21.000Z"},{"id":60,"stock_tickers":"ABT.AX","price_date":"1469721600000","price_close":0.84,"price_high":0.84,"price_low":0.8,"price_open":0.84,"volume":27900.0,"updated_at":"2017-05-09T13:46:21.000Z"},{"id":61,"stock_tickers":"ABT.AX","price_date":"1469980800000","price_close":0.88,"price_high":0.88,"price_low":0.88,"price_open":0.88,"volume":1100.0,"updated_at":"2017-05-09T13:46:21.000Z"},{"id":62,"stock_tickers":"ABT.AX","price_date":"1470067200000","price_close":0.88,"price_high":0.88,"price_low":0.88,"price_open":0.88,"volume":3700.0,"updated_at":"2017-05-09T13:46:21.000Z"},{"id":63,"stock_tickers":"ABT.AX","price_date":"1470153600000","price_close":0.8,"price_high":0.865,"price_low":0.8,"price_open":0.865,"volume":42200.0,"updated_at":"2017-05-09T13:46:21.000Z"},{"id":64,"stock_tickers":"ABT.AX","price_date":"1470240000000","price_close":0.8,"price_high":0.8,"price_low":0.8,"price_open":0.8,"volume":600.0,"updated_at":"2017-05-09T13:46:21.000Z"},{"id":65,"stock_tickers":"ABT.AX","price_date":"1470326400000","price_close":0.8,"price_high":0.835,"price_low":0.8,"price_open":0.8,"volume":17400.0,"updated_at":"2017-05-09T13:46:21.000Z"},{"id":66,"stock_tickers":"ABT.AX","price_date":"1470585600000","price_close":0.87,"price_high":0.87,"price_low":0.8,"price_open":0.8,"volume":29900.0,"updated_at":"2017-05-09T13:46:21.000Z"},{"id":67,"stock_tickers":"ABT.AX","price_date":"1470672000000","price_close":0.88,"price_high":0.88,"price_low":0.88,"price_open":0.88,"volume":22700.0,"updated_at":"2017-05-09T13:46:21.000Z"},{"id":68,"stock_tickers":"ABT.AX","price_date":"1470758400000","price_close":0.88,"price_high":0.88,"price_low":0.88,"price_open":0.88,"volume":17800.0,"updated_at":"2017-05-09T13:46:21.000Z"},{"id":69,"stock_tickers":"ABT.AX","price_date":"1470844800000","price_close":0.88,"price_high":0.88,"price_low":0.88,"price_open":0.88,"volume":14700.0,"updated_at":"2017-05-09T13:46:21.000Z"},{"id":70,"stock_tickers":"ABT.AX","price_date":"1470931200000","price_close":0.88,"price_high":0.88,"price_low":0.88,"price_open":0.88,"volume":10000.0,"updated_at":"2017-05-09T13:46:21.000Z"},{"id":71,"stock_tickers":"ABT.AX","price_date":"1471190400000","price_close":0.86,"price_high":0.86,"price_low":0.86,"price_open":0.86,"volume":9800.0,"updated_at":"2017-05-09T13:46:21.000Z"},{"id":72,"stock_tickers":"ABT.AX","price_date":"1471276800000","price_close":0.83,"price_high":0.86,"price_low":0.83,"price_open":0.86,"volume":7100.0,"updated_at":"2017-05-09T13:46:21.000Z"},{"id":73,"stock_tickers":"ABT.AX","price_date":"1471363200000","price_close":0.83,"price_high":0.83,"price_low":0.83,"price_open":0.83,"volume":7000.0,"updated_at":"2017-05-09T13:46:21.000Z"},{"id":74,"stock_tickers":"ABT.AX","price_date":"1471449600000","price_close":0.88,"price_high":0.88,"price_low":0.835,"price_open":0.835,"volume":4700.0,"updated_at":"2017-05-09T13:46:21.000Z"},{"id":75,"stock_tickers":"ABT.AX","price_date":"1471536000000","price_close":0.84,"price_high":0.89,"price_low":0.84,"price_open":0.89,"volume":20900.0,"updated_at":"2017-05-09T13:46:21.000Z"},{"id":76,"stock_tickers":"ABT.AX","price_date":"1471795200000","price_close":0.9,"price_high":0.9,"price_low":0.85,"price_open":0.85,"volume":22800.0,"updated_at":"2017-05-09T13:46:21.000Z"},{"id":77,"stock_tickers":"ABT.AX","price_date":"1471881600000","price_close":0.93,"price_high":0.96,"price_low":0.9,"price_open":0.9,"volume":85900.0,"updated_at":"2017-05-09T13:46:21.000Z"},{"id":78,"stock_tickers":"ABT.AX","price_date":"1471968000000","price_close":0.96,"price_high":0.96,"price_low":0.935,"price_open":0.95,"volume":36500.0,"updated_at":"2017-05-09T13:46:21.000Z"},{"id":79,"stock_tickers":"ABT.AX","price_date":"1472054400000","price_close":0.95,"price_high":0.96,"price_low":0.95,"price_open":0.96,"volume":50000.0,"updated_at":"2017-05-09T13:46:21.000Z"},{"id":80,"stock_tickers":"ABT.AX","price_date":"1472140800000","price_close":0.92,"price_high":0.97,"price_low":0.92,"price_open":0.97,"volume":14300.0,"updated_at":"2017-05-09T13:46:21.000Z"},{"id":81,"stock_tickers":"ABT.AX","price_date":"1472400000000","price_close":0.97,"price_high":0.99,"price_low":0.97,"price_open":0.97,"volume":22000.0,"updated_at":"2017-05-09T13:46:21.000Z"},{"id":82,"stock_tickers":"ABT.AX","price_date":"1472486400000","price_close":0.98,"price_high":0.98,"price_low":0.97,"price_open":0.97,"volume":4200.0,"updated_at":"2017-05-09T13:46:21.000Z"},{"id":83,"stock_tickers":"ABT.AX","price_date":"1472572800000","price_close":0.9,"price_high":0.97,"price_low":0.9,"price_open":0.97,"volume":86600.0,"updated_at":"2017-05-09T13:46:21.000Z"},{"id":84,"stock_tickers":"ABT.AX","price_date":"1472659200000","price_close":0.9,"price_high":0.9,"price_low":0.9,"price_open":0.9,"volume":5000.0,"updated_at":"2017-05-09T13:46:21.000Z"},{"id":85,"stock_tickers":"ABT.AX","price_date":"1472745600000","price_close":0.9,"price_high":0.9,"price_low":0.9,"price_open":0.9,"volume":0.0,"updated_at":"2017-05-09T13:46:21.000Z"},{"id":86,"stock_tickers":"ABT.AX","price_date":"1473004800000","price_close":0.88,"price_high":0.885,"price_low":0.88,"price_open":0.885,"volume":2900.0,"updated_at":"2017-05-09T13:46:21.000Z"},{"id":87,"stock_tickers":"ABT.AX","price_date":"1473091200000","price_close":0.9,"price_high":0.9,"price_low":0.9,"price_open":0.9,"volume":9900.0,"updated_at":"2017-05-09T13:46:21.000Z"},{"id":88,"stock_tickers":"ABT.AX","price_date":"1473177600000","price_close":0.93,"price_high":0.93,"price_low":0.93,"price_open":0.93,"volume":4500.0,"updated_at":"2017-05-09T13:46:21.000Z"},{"id":89,"stock_tickers":"ABT.AX","price_date":"1473264000000","price_close":0.9,"price_high":0.93,"price_low":0.9,"price_open":0.93,"volume":7200.0,"updated_at":"2017-05-09T13:46:21.000Z"},{"id":90,"stock_tickers":"ABT.AX","price_date":"1473350400000","price_close":0.9,"price_high":0.9,"price_low":0.9,"price_open":0.9,"volume":4300.0,"updated_at":"2017-05-09T13:46:21.000Z"},{"id":91,"stock_tickers":"ABT.AX","price_date":"1473609600000","price_close":0.86,"price_high":0.89,"price_low":0.86,"price_open":0.89,"volume":26500.0,"updated_at":"2017-05-09T13:46:21.000Z"},{"id":92,"stock_tickers":"ABT.AX","price_date":"1473696000000","price_close":0.845,"price_high":0.86,"price_low":0.845,"price_open":0.86,"volume":10800.0,"updated_at":"2017-05-09T13:46:21.000Z"},{"id":93,"stock_tickers":"ABT.AX","price_date":"1473782400000","price_close":0.845,"price_high":0.88,"price_low":0.845,"price_open":0.88,"volume":17400.0,"updated_at":"2017-05-09T13:46:21.000Z"},{"id":94,"stock_tickers":"ABT.AX","price_date":"1473868800000","price_close":0.8,"price_high":0.88,"price_low":0.8,"price_open":0.87,"volume":83200.0,"updated_at":"2017-05-09T13:46:21.000Z"},{"id":95,"stock_tickers":"ABT.AX","price_date":"1473955200000","price_close":0.815,"price_high":0.85,"price_low":0.8,"price_open":0.8,"volume":4100.0,"updated_at":"2017-05-09T13:46:21.000Z"},{"id":96,"stock_tickers":"ABT.AX","price_date":"1474214400000","price_close":0.815,"price_high":0.815,"price_low":0.815,"price_open":0.815,"volume":0.0,"updated_at":"2017-05-09T13:46:21.000Z"},{"id":97,"stock_tickers":"ABT.AX","price_date":"1474300800000","price_close":0.83,"price_high":0.83,"price_low":0.82,"price_open":0.825,"volume":15000.0,"updated_at":"2017-05-09T13:46:21.000Z"},{"id":98,"stock_tickers":"ABT.AX","price_date":"1474387200000","price_close":0.82,"price_high":0.83,"price_low":0.82,"price_open":0.83,"volume":16000.0,"updated_at":"2017-05-09T13:46:21.000Z"},{"id":99,"stock_tickers":"ABT.AX","price_date":"1474473600000","price_close":0.87,"price_high":0.87,"price_low":0.82,"price_open":0.825,"volume":57500.0,"updated_at":"2017-05-09T13:46:21.000Z"},{"id":100,"stock_tickers":"ABT.AX","price_date":"1474560000000","price_close":0.9,"price_high":0.9,"price_low":0.87,"price_open":0.87,"volume":24100.0,"updated_at":"2017-05-09T13:46:21.000Z"},{"id":101,"stock_tickers":"ABT.AX","price_date":"1474819200000","price_close":0.9,"price_high":0.9,"price_low":0.9,"price_open":0.9,"volume":0.0,"updated_at":"2017-05-09T13:46:21.000Z"},{"id":102,"stock_tickers":"ABT.AX","price_date":"1474905600000","price_close":0.87,"price_high":0.87,"price_low":0.825,"price_open":0.825,"volume":73500.0,"updated_at":"2017-05-09T13:46:21.000Z"},{"id":103,"stock_tickers":"ABT.AX","price_date":"1474992000000","price_close":0.87,"price_high":0.87,"price_low":0.87,"price_open":0.87,"volume":5000.0,"updated_at":"2017-05-09T13:46:21.000Z"},{"id":104,"stock_tickers":"ABT.AX","price_date":"1475078400000","price_close":0.885,"price_high":0.885,"price_low":0.87,"price_open":0.875,"volume":12600.0,"updated_at":"2017-05-09T13:46:21.000Z"},{"id":105,"stock_tickers":"ABT.AX","price_date":"1475164800000","price_close":0.825,"price_high":0.825,"price_low":0.81,"price_open":0.825,"volume":60700.0,"updated_at":"2017-05-09T13:46:21.000Z"},{"id":106,"stock_tickers":"ABT.AX","price_date":"1475424000000","price_close":0.825,"price_high":0.825,"price_low":0.825,"price_open":0.825,"volume":0.0,"updated_at":"2017-05-09T13:46:21.000Z"},{"id":107,"stock_tickers":"ABT.AX","price_date":"1475510400000","price_close":0.81,"price_high":0.82,"price_low":0.8,"price_open":0.82,"volume":18500.0,"updated_at":"2017-05-09T13:46:21.000Z"},{"id":108,"stock_tickers":"ABT.AX","price_date":"1475596800000","price_close":0.81,"price_high":0.81,"price_low":0.81,"price_open":0.81,"volume":0.0,"updated_at":"2017-05-09T13:46:21.000Z"},{"id":109,"stock_tickers":"ABT.AX","price_date":"1475683200000","price_close":0.81,"price_high":0.81,"price_low":0.81,"price_open":0.81,"volume":0.0,"updated_at":"2017-05-09T13:46:21.000Z"},{"id":110,"stock_tickers":"ABT.AX","price_date":"1475769600000","price_close":0.815,"price_high":0.815,"price_low":0.81,"price_open":0.815,"volume":27400.0,"updated_at":"2017-05-09T13:46:21.000Z"},{"id":111,"stock_tickers":"ABT.AX","price_date":"1476028800000","price_close":0.8,"price_high":0.815,"price_low":0.79,"price_open":0.815,"volume":44200.0,"updated_at":"2017-05-09T13:46:21.000Z"},{"id":112,"stock_tickers":"ABT.AX","price_date":"1476115200000","price_close":0.79,"price_high":0.8,"price_low":0.78,"price_open":0.8,"volume":70900.0,"updated_at":"2017-05-09T13:46:21.000Z"},{"id":113,"stock_tickers":"ABT.AX","price_date":"1476201600000","price_close":0.78,"price_high":0.79,"price_low":0.78,"price_open":0.78,"volume":33500.0,"updated_at":"2017-05-09T13:46:21.000Z"},{"id":114,"stock_tickers":"ABT.AX","price_date":"1476288000000","price_close":0.74,"price_high":0.77,"price_low":0.7,"price_open":0.77,"volume":15000.0,"updated_at":"2017-05-09T13:46:21.000Z"},{"id":115,"stock_tickers":"ABT.AX","price_date":"1476374400000","price_close":0.73,"price_high":0.75,"price_low":0.73,"price_open":0.74,"volume":34600.0,"updated_at":"2017-05-09T13:46:21.000Z"},{"id":116,"stock_tickers":"ABT.AX","price_date":"1476633600000","price_close":0.78,"price_high":0.78,"price_low":0.715,"price_open":0.73,"volume":7600.0,"updated_at":"2017-05-09T13:46:21.000Z"},{"id":117,"stock_tickers":"ABT.AX","price_date":"1476720000000","price_close":0.74,"price_high":0.74,"price_low":0.74,"price_open":0.74,"volume":13200.0,"updated_at":"2017-05-09T13:46:21.000Z"},{"id":118,"stock_tickers":"ABT.AX","price_date":"1476806400000","price_close":0.74,"price_high":0.77,"price_low":0.74,"price_open":0.75,"volume":9100.0,"updated_at":"2017-05-09T13:46:21.000Z"},{"id":119,"stock_tickers":"ABT.AX","price_date":"1476892800000","price_close":0.74,"price_high":0.75,"price_low":0.74,"price_open":0.745,"volume":15800.0,"updated_at":"2017-05-09T13:46:21.000Z"},{"id":120,"stock_tickers":"ABT.AX","price_date":"1476979200000","price_close":0.72,"price_high":0.77,"price_low":0.72,"price_open":0.745,"volume":77100.0,"updated_at":"2017-05-09T13:46:21.000Z"},{"id":121,"stock_tickers":"ABT.AX","price_date":"1477238400000","price_close":0.72,"price_high":0.72,"price_low":0.72,"price_open":0.72,"volume":700.0,"updated_at":"2017-05-09T13:46:21.000Z"},{"id":122,"stock_tickers":"ABT.AX","price_date":"1477324800000","price_close":0.69,"price_high":0.72,"price_low":0.69,"price_open":0.72,"volume":50500.0,"updated_at":"2017-05-09T13:46:21.000Z"},{"id":123,"stock_tickers":"ABT.AX","price_date":"1477411200000","price_close":0.7,"price_high":0.7,"price_low":0.65,"price_open":0.69,"volume":33300.0,"updated_at":"2017-05-09T13:46:21.000Z"},{"id":124,"stock_tickers":"ABT.AX","price_date":"1477497600000","price_close":0.78,"price_high":0.78,"price_low":0.74,"price_open":0.74,"volume":24400.0,"updated_at":"2017-05-09T13:46:21.000Z"},{"id":125,"stock_tickers":"ABT.AX","price_date":"1477584000000","price_close":0.72,"price_high":0.72,"price_low":0.72,"price_open":0.72,"volume":5200.0,"updated_at":"2017-05-09T13:46:21.000Z"},{"id":126,"stock_tickers":"ABT.AX","price_date":"1477843200000","price_close":0.72,"price_high":0.72,"price_low":0.72,"price_open":0.72,"volume":0.0,"updated_at":"2017-05-09T13:46:21.000Z"},{"id":127,"stock_tickers":"ABT.AX","price_date":"1477929600000","price_close":0.72,"price_high":0.72,"price_low":0.72,"price_open":0.72,"volume":0.0,"updated_at":"2017-05-09T13:46:21.000Z"},{"id":128,"stock_tickers":"ABT.AX","price_date":"1478016000000","price_close":0.72,"price_high":0.72,"price_low":0.72,"price_open":0.72,"volume":0.0,"updated_at":"2017-05-09T13:46:21.000Z"},{"id":129,"stock_tickers":"ABT.AX","price_date":"1478102400000","price_close":0.72,"price_high":0.75,"price_low":0.72,"price_open":0.73,"volume":12700.0,"updated_at":"2017-05-09T13:46:21.000Z"},{"id":130,"stock_tickers":"ABT.AX","price_date":"1478188800000","price_close":0.72,"price_high":0.72,"price_low":0.72,"price_open":0.72,"volume":2000.0,"updated_at":"2017-05-09T13:46:21.000Z"},{"id":131,"stock_tickers":"ABT.AX","price_date":"1478448000000","price_close":0.72,"price_high":0.72,"price_low":0.72,"price_open":0.72,"volume":0.0,"updated_at":"2017-05-09T13:46:21.000Z"},{"id":132,"stock_tickers":"ABT.AX","price_date":"1478534400000","price_close":0.72,"price_high":0.72,"price_low":0.72,"price_open":0.72,"volume":0.0,"updated_at":"2017-05-09T13:46:21.000Z"},{"id":133,"stock_tickers":"ABT.AX","price_date":"1478620800000","price_close":0.69,"price_high":0.72,"price_low":0.65,"price_open":0.715,"volume":65100.0,"updated_at":"2017-05-09T13:46:21.000Z"},{"id":134,"stock_tickers":"ABT.AX","price_date":"1478707200000","price_close":0.65,"price_high":0.69,"price_low":0.65,"price_open":0.69,"volume":101000.0,"updated_at":"2017-05-09T13:46:21.000Z"},{"id":135,"stock_tickers":"ABT.AX","price_date":"1478793600000","price_close":0.6,"price_high":0.69,"price_low":0.6,"price_open":0.69,"volume":30500.0,"updated_at":"2017-05-09T13:46:21.000Z"},{"id":136,"stock_tickers":"ABT.AX","price_date":"1479052800000","price_close":0.6,"price_high":0.6,"price_low":0.6,"price_open":0.6,"volume":2500.0,"updated_at":"2017-05-09T13:46:21.000Z"},{"id":137,"stock_tickers":"ABT.AX","price_date":"1479139200000","price_close":0.61,"price_high":0.61,"price_low":0.6,"price_open":0.6,"volume":10000.0,"updated_at":"2017-05-09T13:46:21.000Z"},{"id":138,"stock_tickers":"ABT.AX","price_date":"1479225600000","price_close":0.61,"price_high":0.61,"price_low":0.61,"price_open":0.61,"volume":0.0,"updated_at":"2017-05-09T13:46:21.000Z"},{"id":139,"stock_tickers":"ABT.AX","price_date":"1479312000000","price_close":0.61,"price_high":0.65,"price_low":0.61,"price_open":0.65,"volume":17000.0,"updated_at":"2017-05-09T13:46:21.000Z"},{"id":140,"stock_tickers":"ABT.AX","price_date":"1479398400000","price_close":0.6,"price_high":0.61,"price_low":0.6,"price_open":0.61,"volume":20300.0,"updated_at":"2017-05-09T13:46:21.000Z"},{"id":141,"stock_tickers":"ABT.AX","price_date":"1479657600000","price_close":0.6,"price_high":0.6,"price_low":0.6,"price_open":0.6,"volume":10000.0,"updated_at":"2017-05-09T13:46:21.000Z"},{"id":142,"stock_tickers":"ABT.AX","price_date":"1479744000000","price_close":0.575,"price_high":0.6,"price_low":0.575,"price_open":0.6,"volume":152000.0,"updated_at":"2017-05-09T13:46:21.000Z"},{"id":143,"stock_tickers":"ABT.AX","price_date":"1479830400000","price_close":0.56,"price_high":0.59,"price_low":0.56,"price_open":0.59,"volume":110500.0,"updated_at":"2017-05-09T13:46:21.000Z"},{"id":144,"stock_tickers":"ABT.AX","price_date":"1479916800000","price_close":0.54,"price_high":0.555,"price_low":0.47,"price_open":0.555,"volume":116800.0,"updated_at":"2017-05-09T13:46:21.000Z"},{"id":145,"stock_tickers":"ABT.AX","price_date":"1480003200000","price_close":0.575,"price_high":0.575,"price_low":0.54,"price_open":0.54,"volume":15200.0,"updated_at":"2017-05-09T13:46:21.000Z"},{"id":146,"stock_tickers":"ABT.AX","price_date":"1480262400000","price_close":0.51,"price_high":0.52,"price_low":0.51,"price_open":0.52,"volume":14500.0,"updated_at":"2017-05-09T13:46:21.000Z"},{"id":147,"stock_tickers":"ABT.AX","price_date":"1480348800000","price_close":0.59,"price_high":0.59,"price_low":0.485,"price_open":0.49,"volume":110900.0,"updated_at":"2017-05-09T13:46:21.000Z"},{"id":148,"stock_tickers":"ABT.AX","price_date":"1480435200000","price_close":0.595,"price_high":0.63,"price_low":0.59,"price_open":0.59,"volume":62600.0,"updated_at":"2017-05-09T13:46:21.000Z"},{"id":149,"stock_tickers":"ABT.AX","price_date":"1480521600000","price_close":0.58,"price_high":0.59,"price_low":0.58,"price_open":0.59,"volume":69100.0,"updated_at":"2017-05-09T13:46:21.000Z"},{"id":150,"stock_tickers":"ABT.AX","price_date":"1480608000000","price_close":0.565,"price_high":0.57,"price_low":0.565,"price_open":0.57,"volume":10400.0,"updated_at":"2017-05-09T13:46:21.000Z"},{"id":151,"stock_tickers":"ABT.AX","price_date":"1480867200000","price_close":0.565,"price_high":0.565,"price_low":0.565,"price_open":0.565,"volume":49900.0,"updated_at":"2017-05-09T13:46:21.000Z"},{"id":152,"stock_tickers":"ABT.AX","price_date":"1480953600000","price_close":0.565,"price_high":0.565,"price_low":0.565,"price_open":0.565,"volume":0.0,"updated_at":"2017-05-09T13:46:21.000Z"},{"id":153,"stock_tickers":"ABT.AX","price_date":"1481040000000","price_close":0.565,"price_high":0.565,"price_low":0.565,"price_open":0.565,"volume":0.0,"updated_at":"2017-05-09T13:46:21.000Z"},{"id":154,"stock_tickers":"ABT.AX","price_date":"1481126400000","price_close":0.57,"price_high":0.57,"price_low":0.565,"price_open":0.565,"volume":47500.0,"updated_at":"2017-05-09T13:46:21.000Z"},{"id":155,"stock_tickers":"ABT.AX","price_date":"1481212800000","price_close":0.57,"price_high":0.57,"price_low":0.57,"price_open":0.57,"volume":0.0,"updated_at":"2017-05-09T13:46:21.000Z"},{"id":156,"stock_tickers":"ABT.AX","price_date":"1481472000000","price_close":0.555,"price_high":0.565,"price_low":0.555,"price_open":0.565,"volume":6100.0,"updated_at":"2017-05-09T13:46:21.000Z"},{"id":157,"stock_tickers":"ABT.AX","price_date":"1481558400000","price_close":0.55,"price_high":0.555,"price_low":0.55,"price_open":0.555,"volume":10500.0,"updated_at":"2017-05-09T13:46:21.000Z"},{"id":158,"stock_tickers":"ABT.AX","price_date":"1481644800000","price_close":0.55,"price_high":0.55,"price_low":0.55,"price_open":0.55,"volume":0.0,"updated_at":"2017-05-09T13:46:21.000Z"},{"id":159,"stock_tickers":"ABT.AX","price_date":"1481731200000","price_close":0.57,"price_high":0.57,"price_low":0.56,"price_open":0.57,"volume":27700.0,"updated_at":"2017-05-09T13:46:21.000Z"},{"id":160,"stock_tickers":"ABT.AX","price_date":"1481817600000","price_close":0.57,"price_high":0.57,"price_low":0.57,"price_open":0.57,"volume":8100.0,"updated_at":"2017-05-09T13:46:21.000Z"},{"id":161,"stock_tickers":"ABT.AX","price_date":"1482076800000","price_close":0.58,"price_high":0.58,"price_low":0.56,"price_open":0.57,"volume":7300.0,"updated_at":"2017-05-09T13:46:21.000Z"},{"id":162,"stock_tickers":"ABT.AX","price_date":"1482163200000","price_close":0.58,"price_high":0.58,"price_low":0.58,"price_open":0.58,"volume":0.0,"updated_at":"2017-05-09T13:46:21.000Z"},{"id":163,"stock_tickers":"ABT.AX","price_date":"1482249600000","price_close":0.56,"price_high":0.56,"price_low":0.56,"price_open":0.56,"volume":27000.0,"updated_at":"2017-05-09T13:46:21.000Z"},{"id":164,"stock_tickers":"ABT.AX","price_date":"1482336000000","price_close":0.575,"price_high":0.575,"price_low":0.575,"price_open":0.575,"volume":900.0,"updated_at":"2017-05-09T13:46:21.000Z"},{"id":165,"stock_tickers":"ABT.AX","price_date":"1482422400000","price_close":0.575,"price_high":0.575,"price_low":0.575,"price_open":0.575,"volume":0.0,"updated_at":"2017-05-09T13:46:21.000Z"},{"id":166,"stock_tickers":"ABT.AX","price_date":"1482681600000","price_close":0.575,"price_high":0.575,"price_low":0.575,"price_open":0.575,"volume":0.0,"updated_at":"2017-05-09T13:46:21.000Z"},{"id":167,"stock_tickers":"ABT.AX","price_date":"1482768000000","price_close":0.575,"price_high":0.575,"price_low":0.575,"price_open":0.575,"volume":0.0,"updated_at":"2017-05-09T13:46:21.000Z"},{"id":168,"stock_tickers":"ABT.AX","price_date":"1482854400000","price_close":0.6,"price_high":0.6,"price_low":0.58,"price_open":0.58,"volume":7600.0,"updated_at":"2017-05-09T13:46:21.000Z"},{"id":169,"stock_tickers":"ABT.AX","price_date":"1482940800000","price_close":0.66,"price_high":0.66,"price_low":0.63,"price_open":0.63,"volume":13800.0,"updated_at":"2017-05-09T13:46:21.000Z"},{"id":170,"stock_tickers":"ABT.AX","price_date":"1483027200000","price_close":0.66,"price_high":0.66,"price_low":0.66,"price_open":0.66,"volume":0.0,"updated_at":"2017-05-09T13:46:21.000Z"},{"id":171,"stock_tickers":"ABT.AX","price_date":"1483286400000","price_close":0.66,"price_high":0.66,"price_low":0.66,"price_open":0.66,"volume":0.0,"updated_at":"2017-05-09T13:46:21.000Z"},{"id":172,"stock_tickers":"ABT.AX","price_date":"1483372800000","price_close":0.67,"price_high":0.67,"price_low":0.66,"price_open":0.66,"volume":11000.0,"updated_at":"2017-05-09T13:46:21.000Z"},{"id":173,"stock_tickers":"ABT.AX","price_date":"1483459200000","price_close":0.75,"price_high":0.75,"price_low":0.67,"price_open":0.67,"volume":44100.0,"updated_at":"2017-05-09T13:46:21.000Z"},{"id":174,"stock_tickers":"ABT.AX","price_date":"1483545600000","price_close":0.75,"price_high":0.75,"price_low":0.75,"price_open":0.75,"volume":0.0,"updated_at":"2017-05-09T13:46:21.000Z"},{"id":175,"stock_tickers":"ABT.AX","price_date":"1483632000000","price_close":0.75,"price_high":0.75,"price_low":0.75,"price_open":0.75,"volume":0.0,"updated_at":"2017-05-09T13:46:21.000Z"},{"id":176,"stock_tickers":"ABT.AX","price_date":"1483891200000","price_close":0.64,"price_high":0.69,"price_low":0.64,"price_open":0.69,"volume":23500.0,"updated_at":"2017-05-09T13:46:21.000Z"},{"id":177,"stock_tickers":"ABT.AX","price_date":"1483977600000","price_close":0.62,"price_high":0.62,"price_low":0.62,"price_open":0.62,"volume":2000.0,"updated_at":"2017-05-09T13:46:21.000Z"},{"id":178,"stock_tickers":"ABT.AX","price_date":"1484064000000","price_close":0.62,"price_high":0.62,"price_low":0.62,"price_open":0.62,"volume":0.0,"updated_at":"2017-05-09T13:46:21.000Z"},{"id":179,"stock_tickers":"ABT.AX","price_date":"1484150400000","price_close":0.62,"price_high":0.62,"price_low":0.62,"price_open":0.62,"volume":0.0,"updated_at":"2017-05-09T13:46:21.000Z"},{"id":180,"stock_tickers":"ABT.AX","price_date":"1484236800000","price_close":0.64,"price_high":0.64,"price_low":0.64,"price_open":0.64,"volume":10300.0,"updated_at":"2017-05-09T13:46:21.000Z"},{"id":181,"stock_tickers":"ABT.AX","price_date":"1484496000000","price_close":0.6,"price_high":0.62,"price_low":0.6,"price_open":0.62,"volume":10000.0,"updated_at":"2017-05-09T13:46:21.000Z"},{"id":182,"stock_tickers":"ABT.AX","price_date":"1484582400000","price_close":0.6,"price_high":0.6,"price_low":0.6,"price_open":0.6,"volume":0.0,"updated_at":"2017-05-09T13:46:21.000Z"},{"id":183,"stock_tickers":"ABT.AX","price_date":"1484668800000","price_close":0.6,"price_high":0.6,"price_low":0.6,"price_open":0.6,"volume":0.0,"updated_at":"2017-05-09T13:46:21.000Z"},{"id":184,"stock_tickers":"ABT.AX","price_date":"1484755200000","price_close":0.58,"price_high":0.58,"price_low":0.565,"price_open":0.58,"volume":19000.0,"updated_at":"2017-05-09T13:46:21.000Z"},{"id":185,"stock_tickers":"ABT.AX","price_date":"1484841600000","price_close":0.565,"price_high":0.565,"price_low":0.565,"price_open":0.565,"volume":600.0,"updated_at":"2017-05-09T13:46:21.000Z"},{"id":186,"stock_tickers":"ABT.AX","price_date":"1485100800000","price_close":0.59,"price_high":0.59,"price_low":0.565,"price_open":0.59,"volume":48700.0,"updated_at":"2017-05-09T13:46:21.000Z"},{"id":187,"stock_tickers":"ABT.AX","price_date":"1485187200000","price_close":0.59,"price_high":0.59,"price_low":0.59,"price_open":0.59,"volume":0.0,"updated_at":"2017-05-09T13:46:21.000Z"},{"id":188,"stock_tickers":"ABT.AX","price_date":"1485273600000","price_close":0.54,"price_high":0.56,"price_low":0.53,"price_open":0.56,"volume":50700.0,"updated_at":"2017-05-09T13:46:21.000Z"},{"id":189,"stock_tickers":"ABT.AX","price_date":"1485360000000","price_close":0.54,"price_high":0.54,"price_low":0.54,"price_open":0.54,"volume":0.0,"updated_at":"2017-05-09T13:46:21.000Z"},{"id":190,"stock_tickers":"ABT.AX","price_date":"1485446400000","price_close":0.6,"price_high":0.6,"price_low":0.55,"price_open":0.55,"volume":34500.0,"updated_at":"2017-05-09T13:46:21.000Z"},{"id":191,"stock_tickers":"ABT.AX","price_date":"1485705600000","price_close":0.55,"price_high":0.55,"price_low":0.55,"price_open":0.55,"volume":20800.0,"updated_at":"2017-05-09T13:46:21.000Z"},{"id":192,"stock_tickers":"ABT.AX","price_date":"1485792000000","price_close":0.55,"price_high":0.55,"price_low":0.55,"price_open":0.55,"volume":0.0,"updated_at":"2017-05-09T13:46:21.000Z"},{"id":193,"stock_tickers":"ABT.AX","price_date":"1485878400000","price_close":0.55,"price_high":0.56,"price_low":0.55,"price_open":0.56,"volume":6500.0,"updated_at":"2017-05-09T13:46:21.000Z"},{"id":194,"stock_tickers":"ABT.AX","price_date":"1485964800000","price_close":0.55,"price_high":0.55,"price_low":0.55,"price_open":0.55,"volume":600.0,"updated_at":"2017-05-09T13:46:21.000Z"},{"id":195,"stock_tickers":"ABT.AX","price_date":"1486051200000","price_close":0.55,"price_high":0.55,"price_low":0.55,"price_open":0.55,"volume":1200.0,"updated_at":"2017-05-09T13:46:21.000Z"},{"id":196,"stock_tickers":"ABT.AX","price_date":"1486310400000","price_close":0.55,"price_high":0.565,"price_low":0.55,"price_open":0.565,"volume":35000.0,"updated_at":"2017-05-09T13:46:21.000Z"},{"id":197,"stock_tickers":"ABT.AX","price_date":"1486396800000","price_close":0.55,"price_high":0.55,"price_low":0.55,"price_open":0.55,"volume":0.0,"updated_at":"2017-05-09T13:46:21.000Z"},{"id":198,"stock_tickers":"ABT.AX","price_date":"1486483200000","price_close":0.55,"price_high":0.55,"price_low":0.55,"price_open":0.55,"volume":0.0,"updated_at":"2017-05-09T13:46:21.000Z"},{"id":199,"stock_tickers":"ABT.AX","price_date":"1486569600000","price_close":0.56,"price_high":0.56,"price_low":0.56,"price_open":0.56,"volume":7800.0,"updated_at":"2017-05-09T13:46:21.000Z"},{"id":200,"stock_tickers":"ABT.AX","price_date":"1486656000000","price_close":0.57,"price_high":0.57,"price_low":0.57,"price_open":0.57,"volume":600.0,"updated_at":"2017-05-09T13:46:21.000Z"},{"id":201,"stock_tickers":"ABT.AX","price_date":"1486915200000","price_close":0.55,"price_high":0.57,"price_low":0.55,"price_open":0.57,"volume":12700.0,"updated_at":"2017-05-09T13:46:21.000Z"},{"id":202,"stock_tickers":"ABT.AX","price_date":"1487001600000","price_close":0.55,"price_high":0.55,"price_low":0.55,"price_open":0.55,"volume":1000.0,"updated_at":"2017-05-09T13:46:21.000Z"},{"id":203,"stock_tickers":"ABT.AX","price_date":"1487088000000","price_close":0.54,"price_high":0.54,"price_low":0.54,"price_open":0.54,"volume":4200.0,"updated_at":"2017-05-09T13:46:21.000Z"},{"id":204,"stock_tickers":"ABT.AX","price_date":"1487174400000","price_close":0.54,"price_high":0.54,"price_low":0.54,"price_open":0.54,"volume":5700.0,"updated_at":"2017-05-09T13:46:21.000Z"},{"id":205,"stock_tickers":"ABT.AX","price_date":"1487260800000","price_close":0.58,"price_high":0.59,"price_low":0.535,"price_open":0.54,"volume":120900.0,"updated_at":"2017-05-09T13:46:21.000Z"},{"id":206,"stock_tickers":"ABT.AX","price_date":"1487520000000","price_close":0.57,"price_high":0.58,"price_low":0.555,"price_open":0.555,"volume":94100.0,"updated_at":"2017-05-09T13:46:21.000Z"},{"id":207,"stock_tickers":"ABT.AX","price_date":"1487606400000","price_close":0.545,"price_high":0.55,"price_low":0.52,"price_open":0.55,"volume":65400.0,"updated_at":"2017-05-09T13:46:21.000Z"},{"id":208,"stock_tickers":"ABT.AX","price_date":"1487692800000","price_close":0.51,"price_high":0.51,"price_low":0.51,"price_open":0.51,"volume":3000.0,"updated_at":"2017-05-09T13:46:21.000Z"},{"id":209,"stock_tickers":"ABT.AX","price_date":"1487779200000","price_close":0.525,"price_high":0.525,"price_low":0.505,"price_open":0.505,"volume":15200.0,"updated_at":"2017-05-09T13:46:21.000Z"},{"id":210,"stock_tickers":"ABT.AX","price_date":"1487865600000","price_close":0.5,"price_high":0.52,"price_low":0.5,"price_open":0.52,"volume":47500.0,"updated_at":"2017-05-09T13:46:21.000Z"},{"id":211,"stock_tickers":"ABT.AX","price_date":"1488124800000","price_close":0.5,"price_high":0.5,"price_low":0.5,"price_open":0.5,"volume":1500.0,"updated_at":"2017-05-09T13:46:21.000Z"},{"id":212,"stock_tickers":"ABT.AX","price_date":"1488211200000","price_close":0.52,"price_high":0.52,"price_low":0.52,"price_open":0.52,"volume":3000.0,"updated_at":"2017-05-09T13:46:21.000Z"},{"id":213,"stock_tickers":"ABT.AX","price_date":"1488297600000","price_close":0.52,"price_high":0.52,"price_low":0.52,"price_open":0.52,"volume":0.0,"updated_at":"2017-05-09T13:46:21.000Z"},{"id":214,"stock_tickers":"ABT.AX","price_date":"1488384000000","price_close":0.475,"price_high":0.475,"price_low":0.475,"price_open":0.475,"volume":1000.0,"updated_at":"2017-05-09T13:46:21.000Z"},{"id":215,"stock_tickers":"ABT.AX","price_date":"1488470400000","price_close":0.49,"price_high":0.52,"price_low":0.48,"price_open":0.51,"volume":43600.0,"updated_at":"2017-05-09T13:46:21.000Z"},{"id":216,"stock_tickers":"ABT.AX","price_date":"1488729600000","price_close":0.49,"price_high":0.49,"price_low":0.49,"price_open":0.49,"volume":0.0,"updated_at":"2017-05-09T13:46:21.000Z"},{"id":217,"stock_tickers":"ABT.AX","price_date":"1488816000000","price_close":0.49,"price_high":0.49,"price_low":0.49,"price_open":0.49,"volume":0.0,"updated_at":"2017-05-09T13:46:21.000Z"},{"id":218,"stock_tickers":"ABT.AX","price_date":"1488902400000","price_close":0.49,"price_high":0.49,"price_low":0.49,"price_open":0.49,"volume":0.0,"updated_at":"2017-05-09T13:46:21.000Z"},{"id":219,"stock_tickers":"ABT.AX","price_date":"1488988800000","price_close":0.5,"price_high":0.5,"price_low":0.495,"price_open":0.495,"volume":45400.0,"updated_at":"2017-05-09T13:46:21.000Z"},{"id":220,"stock_tickers":"ABT.AX","price_date":"1489075200000","price_close":0.49,"price_high":0.5,"price_low":0.49,"price_open":0.5,"volume":50900.0,"updated_at":"2017-05-09T13:46:21.000Z"},{"id":221,"stock_tickers":"ABT.AX","price_date":"1489334400000","price_close":0.49,"price_high":0.49,"price_low":0.49,"price_open":0.49,"volume":6200.0,"updated_at":"2017-05-09T13:46:21.000Z"},{"id":222,"stock_tickers":"ABT.AX","price_date":"1489420800000","price_close":0.495,"price_high":0.51,"price_low":0.495,"price_open":0.5,"volume":14400.0,"updated_at":"2017-05-09T13:46:21.000Z"},{"id":223,"stock_tickers":"ABT.AX","price_date":"1489507200000","price_close":0.52,"price_high":0.52,"price_low":0.51,"price_open":0.51,"volume":40000.0,"updated_at":"2017-05-09T13:46:21.000Z"},{"id":224,"stock_tickers":"ABT.AX","price_date":"1489593600000","price_close":0.52,"price_high":0.525,"price_low":0.52,"price_open":0.52,"volume":33300.0,"updated_at":"2017-05-09T13:46:21.000Z"},{"id":225,"stock_tickers":"ABT.AX","price_date":"1489680000000","price_close":0.55,"price_high":0.56,"price_low":0.55,"price_open":0.56,"volume":29000.0,"updated_at":"2017-05-09T13:46:21.000Z"},{"id":226,"stock_tickers":"ABT.AX","price_date":"1489939200000","price_close":0.55,"price_high":0.55,"price_low":0.55,"price_open":0.55,"volume":700.0,"updated_at":"2017-05-09T13:46:21.000Z"},{"id":227,"stock_tickers":"ABT.AX","price_date":"1490025600000","price_close":0.52,"price_high":0.55,"price_low":0.52,"price_open":0.55,"volume":11900.0,"updated_at":"2017-05-09T13:46:21.000Z"},{"id":228,"stock_tickers":"ABT.AX","price_date":"1490112000000","price_close":0.52,"price_high":0.52,"price_low":0.52,"price_open":0.52,"volume":0.0,"updated_at":"2017-05-09T13:46:21.000Z"},{"id":229,"stock_tickers":"ABT.AX","price_date":"1490198400000","price_close":0.52,"price_high":0.52,"price_low":0.52,"price_open":0.52,"volume":0.0,"updated_at":"2017-05-09T13:46:21.000Z"},{"id":230,"stock_tickers":"ABT.AX","price_date":"1490284800000","price_close":0.52,"price_high":0.52,"price_low":0.52,"price_open":0.52,"volume":1000.0,"updated_at":"2017-05-09T13:46:21.000Z"},{"id":231,"stock_tickers":"ABT.AX","price_date":"1490544000000","price_close":0.52,"price_high":0.52,"price_low":0.52,"price_open":0.52,"volume":0.0,"updated_at":"2017-05-09T13:46:21.000Z"},{"id":232,"stock_tickers":"ABT.AX","price_date":"1490630400000","price_close":0.505,"price_high":0.52,"price_low":0.505,"price_open":0.52,"volume":2000.0,"updated_at":"2017-05-09T13:46:21.000Z"},{"id":233,"stock_tickers":"ABT.AX","price_date":"1490716800000","price_close":0.505,"price_high":0.505,"price_low":0.505,"price_open":0.505,"volume":0.0,"updated_at":"2017-05-09T13:46:21.000Z"},{"id":234,"stock_tickers":"ABT.AX","price_date":"1490803200000","price_close":0.49,"price_high":0.505,"price_low":0.48,"price_open":0.505,"volume":81300.0,"updated_at":"2017-05-09T13:46:21.000Z"},{"id":235,"stock_tickers":"ABT.AX","price_date":"1490889600000","price_close":0.5,"price_high":0.5,"price_low":0.43,"price_open":0.45,"volume":24800.0,"updated_at":"2017-05-09T13:46:21.000Z"},{"id":236,"stock_tickers":"ABT.AX","price_date":"1491148800000","price_close":0.5,"price_high":0.5,"price_low":0.5,"price_open":0.5,"volume":0.0,"updated_at":"2017-05-09T13:46:21.000Z"},{"id":237,"stock_tickers":"ABT.AX","price_date":"1491235200000","price_close":0.48,"price_high":0.48,"price_low":0.48,"price_open":0.48,"volume":700.0,"updated_at":"2017-05-09T13:46:21.000Z"},{"id":238,"stock_tickers":"ABT.AX","price_date":"1491321600000","price_close":0.48,"price_high":0.48,"price_low":0.48,"price_open":0.48,"volume":0.0,"updated_at":"2017-05-09T13:46:21.000Z"},{"id":239,"stock_tickers":"ABT.AX","price_date":"1491408000000","price_close":0.45,"price_high":0.48,"price_low":0.45,"price_open":0.465,"volume":47800.0,"updated_at":"2017-05-09T13:46:21.000Z"},{"id":240,"stock_tickers":"ABT.AX","price_date":"1491494400000","price_close":0.43,"price_high":0.46,"price_low":0.41,"price_open":0.46,"volume":53000.0,"updated_at":"2017-05-09T13:46:21.000Z"},{"id":241,"stock_tickers":"ABT.AX","price_date":"1491753600000","price_close":0.39,"price_high":0.42,"price_low":0.39,"price_open":0.41,"volume":20100.0,"updated_at":"2017-05-09T13:46:21.000Z"},{"id":242,"stock_tickers":"ABT.AX","price_date":"1491840000000","price_close":0.35,"price_high":0.39,"price_low":0.35,"price_open":0.39,"volume":41000.0,"updated_at":"2017-05-09T13:46:21.000Z"},{"id":243,"stock_tickers":"ABT.AX","price_date":"1491926400000","price_close":0.4,"price_high":0.4,"price_low":0.36,"price_open":0.36,"volume":18500.0,"updated_at":"2017-05-09T13:46:21.000Z"},{"id":244,"stock_tickers":"ABT.AX","price_date":"1492012800000","price_close":0.515,"price_high":0.53,"price_low":0.445,"price_open":0.445,"volume":163800.0,"updated_at":"2017-05-09T13:46:21.000Z"},{"id":245,"stock_tickers":"ABT.AX","price_date":"1492099200000","price_close":0.515,"price_high":0.515,"price_low":0.515,"price_open":0.515,"volume":0.0,"updated_at":"2017-05-09T13:46:21.000Z"},{"id":246,"stock_tickers":"ABT.AX","price_date":"1492358400000","price_close":0.515,"price_high":0.515,"price_low":0.515,"price_open":0.515,"volume":0.0,"updated_at":"2017-05-09T13:46:21.000Z"},{"id":247,"stock_tickers":"ABT.AX","price_date":"1492444800000","price_close":0.45,"price_high":0.515,"price_low":0.45,"price_open":0.515,"volume":23100.0,"updated_at":"2017-05-09T13:46:21.000Z"},{"id":248,"stock_tickers":"ABT.AX","price_date":"1492531200000","price_close":0.45,"price_high":0.45,"price_low":0.45,"price_open":0.45,"volume":0.0,"updated_at":"2017-05-09T13:46:21.000Z"},{"id":249,"stock_tickers":"ABT.AX","price_date":"1492617600000","price_close":0.5,"price_high":0.515,"price_low":0.475,"price_open":0.475,"volume":62700.0,"updated_at":"2017-05-09T13:46:21.000Z"},{"id":250,"stock_tickers":"ABT.AX","price_date":"1492704000000","price_close":0.47,"price_high":0.47,"price_low":0.47,"price_open":0.47,"volume":3000.0,"updated_at":"2017-05-09T13:46:21.000Z"},{"id":251,"stock_tickers":"ABT.AX","price_date":"1492963200000","price_close":0.43,"price_high":0.44,"price_low":0.43,"price_open":0.44,"volume":17200.0,"updated_at":"2017-05-09T13:46:21.000Z"},{"id":252,"stock_tickers":"ABT.AX","price_date":"1493049600000","price_close":0.43,"price_high":0.43,"price_low":0.43,"price_open":0.43,"volume":0.0,"updated_at":"2017-05-09T13:46:21.000Z"},{"id":253,"stock_tickers":"ABT.AX","price_date":"1493136000000","price_close":0.44,"price_high":0.44,"price_low":0.44,"price_open":0.44,"volume":700.0,"updated_at":"2017-05-09T13:46:21.000Z"},{"id":254,"stock_tickers":"ABT.AX","price_date":"1493222400000","price_close":0.46,"price_high":0.46,"price_low":0.46,"price_open":0.46,"volume":4500.0,"updated_at":"2017-05-09T13:46:21.000Z"},{"id":255,"stock_tickers":"ABT.AX","price_date":"1493308800000","price_close":0.47,"price_high":0.47,"price_low":0.43,"price_open":0.45,"volume":25500.0,"updated_at":"2017-05-09T13:46:21.000Z"},{"id":256,"stock_tickers":"ABT.AX","price_date":"1493568000000","price_close":0.47,"price_high":0.47,"price_low":0.47,"price_open":0.47,"volume":0.0,"updated_at":"2017-05-09T13:46:21.000Z"},{"id":257,"stock_tickers":"ABT.AX","price_date":"1493654400000","price_close":0.47,"price_high":0.47,"price_low":0.47,"price_open":0.47,"volume":0.0,"updated_at":"2017-05-09T13:46:21.000Z"},{"id":258,"stock_tickers":"ABT.AX","price_date":"1493740800000","price_close":0.365,"price_high":0.42,"price_low":0.325,"price_open":0.42,"volume":335400.0,"updated_at":"2017-05-09T13:46:21.000Z"},{"id":259,"stock_tickers":"ABT.AX","price_date":"1493827200000","price_close":0.365,"price_high":0.38,"price_low":0.34,"price_open":0.36,"volume":114000.0,"updated_at":"2017-05-09T13:46:21.000Z"},{"id":260,"stock_tickers":"ABT.AX","price_date":"1493913600000","price_close":0.35,"price_high":0.36,"price_low":0.35,"price_open":0.36,"volume":41200.0,"updated_at":"2017-05-09T13:46:21.000Z"},{"id":261,"stock_tickers":"ABT.AX","price_date":"1494172800000","price_close":0.33,"price_high":0.36,"price_low":0.33,"price_open":0.36,"volume":106000.0,"updated_at":"2017-05-09T13:46:21.000Z"}]